kiteconnect/__init__.py
kiteconnect/__version__.py
kiteconnect/connect.py
kiteconnect/exceptions.py
kiteconnect/ticker.py
kiteconnect-5.0.1.dist-info/LICENSE
kiteconnect-5.0.1.dist-info/METADATA
kiteconnect-5.0.1.dist-info/WHEEL
kiteconnect-5.0.1.dist-info/top_level.txt
kiteconnect-5.0.1.dist-info/RECORD
