Metadata-Version: 2.1
Name: kiteconnect
Version: 5.0.1
Summary: The official Python client for the Kite Connect trading API
Home-page: https://kite.trade
Download-URL: https://github.com/zerodhatech/pykiteconnect
Author: Zerodha Technology Pvt. Ltd. (India)
Author-email: talk@zerodha.tech
License: MIT
Classifier: Development Status :: 5 - Production/Stable
Classifier: Intended Audience :: Developers
Classifier: Intended Audience :: Financial and Insurance Industry
Classifier: Programming Language :: Python
Classifier: Natural Language :: English
Classifier: License :: OSI Approved :: MIT License
Classifier: Programming Language :: Python :: 3.5
Classifier: Programming Language :: Python :: 3.6
Classifier: Programming Language :: Python :: 3.7
Classifier: Topic :: Office/Business :: Financial :: Investment
Classifier: Topic :: Software Development :: Libraries :: Python Modules
Classifier: Topic :: Software Development :: Libraries
License-File: LICENSE
Requires-Dist: service_identity>=18.1.0
Requires-Dist: requests>=2.18.4
Requires-Dist: six>=1.11.0
Requires-Dist: pyOpenSSL>=17.5.0
Requires-Dist: python-dateutil>=2.6.1
Requires-Dist: autobahn[twisted]==19.11.2
Provides-Extra: doc
Requires-Dist: pdoc; extra == "doc"
Requires-Dist: pywin32; sys_platform == "win32"
